Metadata-Version: 2.1
Name: tidytext
Version: 0.0.1
Summary: Text processing with pandas DataFrames.
Home-page: https://github.com/machow/tidytuesday-py
Author: Michael Chow
Author-email: mc_al_github@fastmail.com
License: UNKNOWN
Platform: UNKNOWN
